geodrillcalc/__init__.py
geodrillcalc/exceptions.py
geodrillcalc/geodrillcalc_interface.py
geodrillcalc/data/fallback_cost_rates.json
geodrillcalc/data/fallback_margin_rates.json
geodrillcalc/data_management/wellbore_data_store.py
geodrillcalc/utils/__init__.py
geodrillcalc/utils/calc_utils.py
geodrillcalc/utils/cost_utils.py
geodrillcalc/utils/data_preparation.py
geodrillcalc/utils/utils.py
geodrillcalc/utils/validation.py
geodrillcalc/wellborecalc/__init__.py
geodrillcalc/wellborecalc/casing_calculation.py
geodrillcalc/wellborecalc/pump_calculation.py
geodrillcalc/wellborecalc/screen_calculation.py
geodrillcalc/wellborecalc/wellborecalc_pipeline.py
geodrillcalc/wellborecost/__init__.py
geodrillcalc/wellborecost/cost_parameter_extractor.py
geodrillcalc/wellborecost/cost_stage_calculator.py
geodrillcalc/wellborecost/wellborecost_pipeline.py
geodrillcalc-0.5.0a0.dist-info/LICENSE
geodrillcalc-0.5.0a0.dist-info/METADATA
geodrillcalc-0.5.0a0.dist-info/WHEEL
geodrillcalc-0.5.0a0.dist-info/top_level.txt
geodrillcalc-0.5.0a0.dist-info/RECORD
