Metadata-Version: 2.2
Name: geodrillcalc
Version: 0.5.0a0
Summary: Geothermal Wellbore Parameter and Cost Calculation Tool for SGIL Project
Home-page: https://github.com/08dhuh/geodrillcalc
Author: Doran Huh
Author-email: 08dhuh@gmail.com
Classifier: Development Status :: 3 - Alpha
Classifier: Intended Audience :: Developers
Classifier: License :: OSI Approved :: MIT License
Classifier: Programming Language :: Python :: 3.11
Classifier: Topic :: Scientific/Engineering
Requires-Python: >=3.11
License-File: LICENSE
Requires-Dist: numpy>=1.0
Requires-Dist: pandas>=2.0
Dynamic: author
Dynamic: author-email
Dynamic: classifier
Dynamic: description
Dynamic: description-content-type
Dynamic: home-page
Dynamic: requires-dist
Dynamic: requires-python
Dynamic: summary
